Metadata-Version: 1.2
Name: SubScan
Version: 10.0.0
Summary: Module used to find directories and sub-domains of websites
Home-page: https://github.com/Negative-py/SubScan
Author: Negative.py
License: UNKNOWN
Platform: UNKNOWN
Classifier: Programming Language :: Python :: 3
Classifier: License :: OSI Approved :: MIT License
Classifier: Operating System :: OS Independent
Requires-Python: >=3.6
